fastapi_clientify.py
fastapi_clientify-0.0.2.dist-info/LICENSE
fastapi_clientify-0.0.2.dist-info/WHEEL
fastapi_clientify-0.0.2.dist-info/METADATA
fastapi_clientify-0.0.2.dist-info/RECORD
