Metadata-Version: 2.1
Name: fastapi_clientify
Version: 0.0.2
Summary: FastAPI Clientify - Reduce server load using Local Storage
Home-page: https://github.com/hugoduar/fastapi-clientify
License: UNKNOWN
Author: hugoduar
Author-email: hugoduar1@gmail.com
Requires-Python: >=3.5
Classifier: Development Status :: 4 - Beta
Classifier: Programming Language :: Python :: 3 :: Only
Classifier: Programming Language :: Python :: 3.7
Classifier: Programming Language :: Python :: 3.8
Classifier: Programming Language :: Python :: 3.9
Classifier: License :: OSI Approved :: MIT License
Classifier: Topic :: Internet :: WWW/HTTP :: HTTP Servers
Classifier: Intended Audience :: Developers
Project-URL: Documentation, https://fastapi-clientify.readthedocs.io/en/latest/
